grassed/__init__.py
grassed/handlers.py
grassed-1.0.0.dist-info/LICENSE
grassed-1.0.0.dist-info/METADATA
grassed-1.0.0.dist-info/WHEEL
grassed-1.0.0.dist-info/top_level.txt
grassed-1.0.0.dist-info/RECORD
