Metadata-Version: 2.1
Name: grassed
Version: 1.0.0
Summary: Python logger handler that can send messages to a Slack channel.
Home-page: https://github.com/SSlinky/SlackLogger
Author: Sam Vanderslink
Author-email: sam@notis.net.au
License: GPLv3
Keywords: slack,logging handler,logger handler,logger,handler,logging
Platform: UNKNOWN
Classifier: Programming Language :: Python :: 3 :: Only
Classifier: License :: OSI Approved :: GNU General Public License v3 or later (GPLv3+)
Classifier: Operating System :: OS Independent
Classifier: Intended Audience :: Developers
Classifier: Topic :: System :: Logging
Requires-Dist: requests
